agentm_params_client/__init__.py
agentm_params_client/client.py
agentm_params_client/refresh.py
agentm_params_client/runtime.py
agentm_params_client-0.1.10.dist-info/licenses/LICENSE
agentm_params_client-0.1.10.dist-info/METADATA
agentm_params_client-0.1.10.dist-info/WHEEL
agentm_params_client-0.1.10.dist-info/top_level.txt
agentm_params_client-0.1.10.dist-info/RECORD
