Metadata-Version: 2.4
Name: agentm-params-client
Version: 0.1.10
Summary: Client SDK for Agent-M Params service
Author: Agent M
License-Expression: MIT
Project-URL: Homepage, https://github.com/perkail/Agent-M
Keywords: agentm,params,governance,sdk
Requires-Python: >=3.8
License-File: LICENSE
Dynamic: license-file
